datavita/__init__.py
datavita/andes/__init__.py
datavita/andes/andes_apis.py
datavita/andes/andes_data.py
datavita/core/__init__.py
datavita/core/auth.py
datavita/core/common/__init__.py
datavita/core/common/contants.py
datavita/core/exc/__init__.py
datavita/core/exc/exception.py
datavita/core/transport/__init__.py
datavita/core/transport/comrequests.py
datavita/core/transport/http.py
datavita/core/transport/utils.py
datavita/core/typesystem/__init__.py
datavita/core/typesystem/abstract.py
datavita/core/typesystem/encoder.py
datavita/core/typesystem/fields.py
datavita/core/typesystem/schema.py
datavita/core/utils/__init__.py
datavita/core/utils/compat.py
datavita/core/utils/log.py
datavita/core/utils/middleware.py
datavita/factor/__init__.py
datavita_open_python_sdk-0.0.3.dist-info/LICENSE
datavita_open_python_sdk-0.0.3.dist-info/METADATA
datavita_open_python_sdk-0.0.3.dist-info/WHEEL
datavita_open_python_sdk-0.0.3.dist-info/top_level.txt
datavita_open_python_sdk-0.0.3.dist-info/RECORD
